{
  "id": 2987,
  "description": "Cambridge Sesh",
  "user": {
    "id": 1896,
    "name": "steak"
  },
  "players": [
    {
      "id": 1917,
      "name": "tomdidiot"
    },
    {
      "id": 1896,
      "name": "steak"
    },
    {
      "id": 1928,
      "name": "Saintis"
    }
  ],
  "max_players": 3,
  "title": "1846",
  "settings": {
    "seed": 2.227239598434798e+38
  },
  "status": "finished",
  "turn": 6,
  "round": "Operating Round",
  "acting": [
    1917
  ],
  "result": {
    "steak": 7570,
    "Saintis": 6096,
    "tomdidiot": 7766
  },
  "actions": [
    {
      "id": 1,
      "type": "bid",
      "price": 40,
      "entity": "Saintis",
      "company": "MC",
      "entity_type": "player",
      "original_id": 1
    },
    {
      "id": 2,
      "type": "bid",
      "price": 40,
      "entity": "steak",
      "company": "BIG4",
      "entity_type": "player",
      "original_id": 2
    },
    {
      "id": 3,
      "type": "bid",
      "price": 60,
      "entity": "tomdidiot",
      "company": "C&WI",
      "entity_type": "player",
      "original_id": 3
    },
    {
      "id": 4,
      "type": "bid",
      "price": 0,
      "entity": "Saintis",
      "company": "Pass (3)",
      "entity_type": "player",
      "original_id": 4
    },
    {
      "id": 5,
      "type": "bid",
      "price": 60,
      "entity": "steak",
      "company": "MPC",
      "entity_type": "player",
      "original_id": 5
    },
    {
      "id": 6,
      "type": "bid",
      "price": 60,
      "entity": "tomdidiot",
      "company": "MS",
      "entity_type": "player",
      "original_id": 6
    },
    {
      "id": 7,
      "type": "bid",
      "price": 0,
      "entity": "Saintis",
      "company": "Pass (2)",
      "entity_type": "player",
      "original_id": 7
    },
    {
      "id": 8,
      "type": "bid",
      "price": 0,
      "entity": "steak",
      "company": "Pass (1)",
      "entity_type": "player",
      "original_id": 8
    },
    {
      "id": 9,
      "type": "pass",
      "entity": "tomdidiot",
      "entity_type": "player",
      "original_id": 9
    },
    {
      "id": 10,
      "type": "pass",
      "entity": "Saintis",
      "entity_type": "player",
      "original_id": 10
    },
    {
      "id": 11,
      "type": "bid",
      "price": 80,
      "entity": "steak",
      "company": "MAIL",
      "entity_type": "player",
      "original_id": 11
    },
    {
      "id": 12,
      "type": "pass",
      "entity": "tomdidiot",
      "entity_type": "player",
      "original_id": 12
    },
    {
      "id": 13,
      "type": "pass",
      "entity": "steak",
      "entity_type": "player",
      "original_id": 13
    },
    {
      "id": 14,
      "type": "pass",
      "entity": "Saintis",
      "entity_type": "player",
      "original_id": 14
    },
    {
      "id": 15,
      "hex": "B16",
      "tile": "6-0",
      "type": "lay_tile",
      "entity": "MS",
      "rotation": 0,
      "entity_type": "minor",
      "original_id": 15
    },
    {
      "id": 16,
      "type": "pass",
      "entity": "MS",
      "entity_type": "minor",
      "original_id": 16
    },
    {
      "id": 17,
      "type": "run_routes",
      "entity": "MS",
      "routes": [
        {
          "train": "2-0",
          "connections": [
            [
              "C15",
              "B16"
            ]
          ]
        }
      ],
      "entity_type": "minor",
      "original_id": 17
    },
    {
      "id": 18,
      "hex": "G9",
      "tile": "57-0",
      "type": "lay_tile",
      "entity": "BIG4",
      "rotation": 1,
      "entity_type": "minor",
      "original_id": 18
    },
    {
      "id": 19,
      "hex": "G7",
      "tile": "6-1",
      "type": "lay_tile",
      "entity": "BIG4",
      "rotation": 4,
      "entity_type": "minor",
      "original_id": 21
    },
    {
      "id": 20,
      "type": "run_routes",
      "entity": "BIG4",
      "routes": [
        {
          "train": "2-1",
          "connections": [
            [
              "G9",
              "G7"
            ]
          ]
        }
      ],
      "entity_type": "minor",
      "original_id": 22
    },
    {
      "id": 21,
      "hex": "C13",
      "tile": "8-0",
      "type": "lay_tile",
      "entity": "MS",
      "rotation": 4,
      "entity_type": "minor",
      "original_id": 23
    },
    {
      "id": 22,
      "type": "pass",
      "entity": "MS",
      "entity_type": "minor",
      "original_id": 24
    },
    {
      "id": 23,
      "type": "run_routes",
      "entity": "MS",
      "routes": [
        {
          "train": "2-0",
          "connections": [
            [
              "C15",
              "B16"
            ]
          ]
        }
      ],
      "entity_type": "minor",
      "original_id": 25
    },
    {
      "id": 24,
      "hex": "G11",
      "tile": "8-1",
      "type": "lay_tile",
      "entity": "BIG4",
      "rotation": 5,
      "entity_type": "minor",
      "original_id": 26
    },
    {
      "id": 25,
      "type": "run_routes",
      "entity": "BIG4",
      "routes": [
        {
          "train": "2-1",
          "connections": [
            [
              "G9",
              "G7"
            ]
          ]
        }
      ],
      "entity_type": "minor",
      "original_id": 27
    },
    {
      "id": 26,
      "type": "pass",
      "entity": "tomdidiot",
      "entity_type": "player",
      "original_id": 28
    },
    {
      "id": 27,
      "type": "pass",
      "entity": "steak",
      "entity_type": "player",
      "original_id": 29
    },
    {
      "id": 28,
      "type": "par",
      "entity": "Saintis",
      "corporation": "NYC",
      "entity_type": "player",
      "share_price": "90,0,9",
      "original_id": 30
    },
    {
      "id": 29,
      "type": "par",
      "entity": "tomdidiot",
      "corporation": "IC",
      "entity_type": "player",
      "share_price": "90,0,9",
      "original_id": 31
    },
    {
      "id": 30,
      "type": "par",
      "entity": "steak",
      "corporation": "GT",
      "entity_type": "player",
      "share_price": "80,0,8",
      "original_id": 32
    },
    {
      "id": 31,
      "type": "message",
      "entity": "tomdidiot",
      "message": "GT Smells",
      "entity_type": "player",
      "original_id": 33
    },
    {
      "id": 32,
      "type": "buy_shares",
      "entity": "Saintis",
      "shares": [
        "NYC_1"
      ],
      "entity_type": "player",
      "original_id": 34
    },
    {
      "id": 33,
      "type": "buy_shares",
      "entity": "tomdidiot",
      "shares": [
        "IC_1"
      ],
      "entity_type": "player",
      "original_id": 35
    },
    {
      "id": 34,
      "type": "buy_shares",
      "entity": "steak",
      "shares": [
        "GT_1"
      ],
      "entity_type": "player",
      "original_id": 36
    },
    {
      "id": 35,
      "type": "buy_shares",
      "entity": "Saintis",
      "shares": [
        "IC_2"
      ],
      "entity_type": "player",
      "original_id": 37
    },
    {
      "id": 36,
      "type": "pass",
      "entity": "tomdidiot",
      "entity_type": "player",
      "original_id": 38
    },
    {
      "id": 37,
      "type": "pass",
      "entity": "steak",
      "entity_type": "player",
      "original_id": 39
    },
    {
      "id": 38,
      "type": "pass",
      "entity": "Saintis",
      "entity_type": "player",
      "original_id": 40
    },
    {
      "id": 39,
      "hex": "D12",
      "tile": "8-2",
      "type": "lay_tile",
      "entity": "MS",
      "rotation": 1,
      "entity_type": "minor",
      "original_id": 41
    },
    {
      "id": 40,
      "hex": "D10",
      "tile": "8-3",
      "type": "lay_tile",
      "entity": "MS",
      "rotation": 4,
      "entity_type": "minor",
      "original_id": 42
    },
    {
      "id": 41,
      "type": "run_routes",
      "entity": "MS",
      "routes": [
        {
          "train": "2-0",
          "connections": [
            [
              "C15",
              "B16"
            ]
          ]
        }
      ],
      "entity_type": "minor",
      "original_id": 43
    },
    {
      "id": 42,
      "hex": "H6",
      "tile": "7-0",
      "type": "lay_tile",
      "entity": "BIG4",
      "rotation": 2,
      "entity_type": "minor",
      "original_id": 44
    },
    {
      "id": 43,
      "type": "run_routes",
      "entity": "BIG4",
      "routes": [
        {
          "train": "2-1",
          "connections": [
            [
              "G9",
              "G7"
            ]
          ]
        }
      ],
      "entity_type": "minor",
      "original_id": 45
    },
    {
      "id": 44,
      "type": "pass",
      "entity": "NYC",
      "entity_type": "corporation",
      "original_id": 46
    },
    {
      "id": 45,
      "hex": "E19",
      "tile": "8-4",
      "type": "lay_tile",
      "entity": "NYC",
      "rotation": 1,
      "entity_type": "corporation",
      "original_id": 47
    },
    {
      "id": 46,
      "hex": "E17",
      "tile": "293-0",
      "type": "lay_tile",
      "entity": "NYC",
      "rotation": 1,
      "entity_type": "corporation",
      "original_id": 48
    },
    {
      "id": 47,
      "type": "pass",
      "entity": "NYC",
      "entity_type": "corporation",
      "original_id": 49
    },
    {
      "id": 48,
      "type": "buy_train",
      "price": 80,
      "train": "2-2",
      "entity": "NYC",
      "entity_type": "corporation",
      "original_id": 50
    },
    {
      "id": 49,
      "type": "buy_train",
      "price": 80,
      "train": "2-3",
      "entity": "NYC",
      "entity_type": "corporation",
      "original_id": 51
    },
    {
      "id": 50,
      "type": "pass",
      "entity": "NYC",
      "entity_type": "corporation",
      "original_id": 52
    },
    {
      "id": 51,
      "type": "pass",
      "entity": "IC",
      "entity_type": "corporation",
      "original_id": 53
    },
    {
      "id": 52,
      "hex": "J4",
      "tile": "9-0",
      "type": "lay_tile",
      "entity": "IC",
      "rotation": 0,
      "entity_type": "corporation",
      "original_id": 54
    },
    {
      "id": 53,
      "hex": "I3",
      "tile": "9-1",
      "type": "lay_tile",
      "entity": "IC",
      "rotation": 1,
      "entity_type": "corporation",
      "original_id": 55
    },
    {
      "id": 54,
      "city": "I5-0-0",
      "slot": 1,
      "type": "place_token",
      "entity": "IC",
      "entity_type": "corporation",
      "original_id": 56
    },
    {
      "id": 55,
      "type": "buy_train",
      "price": 80,
      "train": "2-4",
      "entity": "IC",
      "entity_type": "corporation",
      "original_id": 57
    },
    {
      "id": 56,
      "type": "buy_train",
      "price": 80,
      "train": "2-5",
      "entity": "IC",
      "entity_type": "corporation",
      "original_id": 58
    },
    {
      "id": 57,
      "type": "pass",
      "entity": "IC",
      "entity_type": "corporation",
      "original_id": 59
    },
    {
      "id": 58,
      "type": "pass",
      "entity": "IC",
      "entity_type": "corporation",
      "original_id": 60
    },
    {
      "id": 59,
      "type": "sell_shares",
      "entity": "GT",
      "shares": [
        "GT_2",
        "GT_3"
      ],
      "percent": 20,
      "entity_type": "corporation",
      "share_price": 70,
      "original_id": 71
    },
    {
      "id": 60,
      "hex": "E9",
      "tile": "7-1",
      "type": "lay_tile",
      "entity": "GT",
      "rotation": 2,
      "entity_type": "corporation",
      "original_id": 72
    },
    {
      "id": 61,
      "hex": "D8",
      "tile": "8-5",
      "type": "lay_tile",
      "entity": "GT",
      "rotation": 5,
      "entity_type": "corporation",
      "original_id": 73
    },
    {
      "id": 62,
      "type": "pass",
      "entity": "GT",
      "entity_type": "corporation",
      "original_id": 74
    },
    {
      "id": 63,
      "type": "buy_train",
      "price": 80,
      "train": "2-6",
      "entity": "GT",
      "entity_type": "corporation",
      "original_id": 75
    },
    {
      "id": 64,
      "type": "buy_train",
      "price": 160,
      "train": "4-0",
      "entity": "GT",
      "variant": "3/5",
      "entity_type": "corporation",
      "original_id": 76
    },
    {
      "id": 65,
      "type": "pass",
      "entity": "GT",
      "entity_type": "corporation",
      "original_id": 77
    },
    {
      "id": 66,
      "type": "pass",
      "entity": "GT",
      "entity_type": "corporation",
      "original_id": 78
    },
    {
      "id": 67,
      "hex": "E9",
      "tile": "28-0",
      "type": "lay_tile",
      "entity": "MS",
      "rotation": 3,
      "entity_type": "minor",
      "original_id": 79
    },
    {
      "id": 68,
      "hex": "E7",
      "tile": "8-6",
      "type": "lay_tile",
      "entity": "MS",
      "rotation": 2,
      "entity_type": "minor",
      "original_id": 80
    },
    {
      "id": 69,
      "type": "run_routes",
      "entity": "MS",
      "routes": [
        {
          "train": "2-0",
          "connections": [
            [
              "C15",
              "B16"
            ]
          ]
        }
      ],
      "entity_type": "minor",
      "original_id": 81
    },
    {
      "id": 70,
      "hex": "H12",
      "tile": "292-0",
      "type": "lay_tile",
      "entity": "BIG4",
      "rotation": 0,
      "entity_type": "minor",
      "original_id": 82
    },
    {
      "id": 71,
      "type": "run_routes",
      "entity": "BIG4",
      "routes": [
        {
          "train": "2-1",
          "connections": [
            [
              "G9",
              "G11",
              "H12"
            ]
          ]
        }
      ],
      "entity_type": "minor",
      "original_id": 83
    },
    {
      "id": 72,
      "type": "pass",
      "entity": "NYC",
      "entity_type": "corporation",
      "original_id": 84
    },
    {
      "id": 73,
      "hex": "D20",
      "tile": "14-0",
      "type": "lay_tile",
      "entity": "NYC",
      "rotation": 0,
      "entity_type": "corporation",
      "original_id": 85
    },
    {
      "id": 74,
      "hex": "E15",
      "tile": "8-7",
      "type": "lay_tile",
      "entity": "NYC",
      "rotation": 2,
      "entity_type": "corporation",
      "original_id": 86
    },
    {
      "id": 75,
      "type": "run_routes",
      "entity": "NYC",
      "routes": [
        {
          "train": "2-2",
          "connections": [
            [
              "C21",
              "D20"
            ]
          ]
        },
        {
          "train": "2-3",
          "connections": [
            [
              "E17",
              "E19",
              "D20"
            ]
          ]
        }
      ],
      "entity_type": "corporation",
      "original_id": 87
    },
    {
      "id": 76,
      "kind": "payout",
      "type": "dividend",
      "entity": "NYC",
      "entity_type": "corporation",
      "original_id": 88
    },
    {
      "id": 77,
      "type": "pass",
      "entity": "NYC",
      "entity_type": "corporation",
      "original_id": 89
    },
    {
      "id": 78,
      "type": "buy_company",
      "price": 40,
      "entity": "NYC",
      "company": "MC",
      "entity_type": "corporation",
      "original_id": 90
    },
    {
      "id": 79,
      "type": "pass",
      "entity": "NYC",
      "entity_type": "corporation",
      "original_id": 91
    },
    {
      "id": 80,
      "type": "pass",
      "entity": "IC",
      "entity_type": "corporation",
      "original_id": 92
    },
    {
      "id": 81,
      "type": "buy_company",
      "price": 60,
      "entity": "IC",
      "company": "MS",
      "entity_type": "corporation",
      "original_id": 93
    },
    {
      "id": 82,
      "type": "buy_company",
      "price": 60,
      "entity": "IC",
      "company": "C&WI",
      "entity_type": "corporation",
      "original_id": 94
    },
    {
      "id": 83,
      "city": "D6-0-3",
      "slot": 0,
      "type": "place_token",
      "entity": "IC",
      "entity_type": "corporation",
      "original_id": 111
    },
    {
      "id": 84,
      "hex": "C15",
      "tile": "295-0",
      "type": "lay_tile",
      "entity": "IC",
      "rotation": 0,
      "entity_type": "corporation",
      "original_id": 120
    },
    {
      "id": 85,
      "type": "pass",
      "entity": "IC",
      "entity_type": "corporation",
      "original_id": 121
    },
    {
      "id": 86,
      "type": "run_routes",
      "entity": "IC",
      "routes": [
        {
          "train": "2-4",
          "connections": [
            [
              "B16",
              "C15"
            ]
          ]
        },
        {
          "train": "2-5",
          "connections": [
            [
              "I5",
              "I3",
              "I1"
            ]
          ]
        }
      ],
      "entity_type": "corporation",
      "original_id": 124
    },
    {
      "id": 87,
      "kind": "payout",
      "type": "dividend",
      "entity": "IC",
      "entity_type": "corporation",
      "original_id": 125
    },
    {
      "id": 88,
      "type": "buy_train",
      "price": 160,
      "train": "4-1",
      "entity": "IC",
      "variant": "3/5",
      "entity_type": "corporation",
      "original_id": 126
    },
    {
      "id": 89,
      "type": "pass",
      "entity": "IC",
      "entity_type": "corporation",
      "original_id": 127
    },
    {
      "id": 90,
      "type": "buy_company",
      "price": 40,
      "entity": "GT",
      "company": "BIG4",
      "entity_type": "corporation",
      "original_id": 128
    },
    {
      "id": 91,
      "type": "buy_company",
      "price": 60,
      "entity": "GT",
      "company": "MAIL",
      "entity_type": "corporation",
      "original_id": 129
    },
    {
      "id": 92,
      "type": "pass",
      "entity": "GT",
      "entity_type": "corporation",
      "original_id": 130
    },
    {
      "id": 93,
      "type": "pass",
      "entity": "GT",
      "entity_type": "corporation",
      "original_id": 131
    },
    {
      "id": 94,
      "type": "run_routes",
      "entity": "GT",
      "routes": [
        {
          "train": "2-6",
          "connections": [
            [
              "B16",
              "C15"
            ]
          ]
        },
        {
          "train": "4-0",
          "connections": [
            [
              "G9",
              "G11",
              "H12"
            ],
            [
              "G9",
              "G7"
            ]
          ]
        }
      ],
      "entity_type": "corporation",
      "original_id": 132
    },
    {
      "id": 95,
      "kind": "payout",
      "type": "dividend",
      "entity": "GT",
      "entity_type": "corporation",
      "original_id": 133
    },
    {
      "id": 96,
      "type": "pass",
      "entity": "GT",
      "entity_type": "corporation",
      "original_id": 134
    },
    {
      "id": 97,
      "type": "buy_company",
      "price": 60,
      "entity": "GT",
      "company": "MPC",
      "entity_type": "corporation",
      "original_id": 135
    },
    {
      "id": 98,
      "type": "buy_shares",
      "entity": "tomdidiot",
      "shares": [
        "IC_3"
      ],
      "entity_type": "player",
      "original_id": 136
    },
    {
      "id": 99,
      "type": "buy_shares",
      "entity": "steak",
      "shares": [
        "IC_4"
      ],
      "entity_type": "player",
      "original_id": 137
    },
    {
      "id": 100,
      "type": "buy_shares",
      "entity": "Saintis",
      "shares": [
        "NYC_2"
      ],
      "entity_type": "player",
      "original_id": 138
    },
    {
      "id": 101,
      "type": "buy_shares",
      "entity": "tomdidiot",
      "shares": [
        "GT_4"
      ],
      "entity_type": "player",
      "original_id": 139
    },
    {
      "id": 102,
      "type": "buy_shares",
      "entity": "steak",
      "shares": [
        "NYC_3"
      ],
      "entity_type": "player",
      "original_id": 140
    },
    {
      "id": 103,
      "type": "pass",
      "entity": "Saintis",
      "entity_type": "player",
      "original_id": 141
    },
    {
      "id": 104,
      "type": "pass",
      "entity": "tomdidiot",
      "entity_type": "player",
      "original_id": 142
    },
    {
      "id": 105,
      "type": "buy_shares",
      "entity": "steak",
      "shares": [
        "GT_2"
      ],
      "entity_type": "player",
      "original_id": 143
    },
    {
      "id": 106,
      "type": "pass",
      "entity": "Saintis",
      "entity_type": "player",
      "original_id": 144
    },
    {
      "id": 107,
      "type": "pass",
      "entity": "tomdidiot",
      "entity_type": "player",
      "original_id": 145
    },
    {
      "id": 108,
      "type": "pass",
      "entity": "steak",
      "entity_type": "player",
      "original_id": 146
    },
    {
      "id": 109,
      "type": "pass",
      "entity": "NYC",
      "entity_type": "corporation",
      "original_id": 161
    },
    {
      "id": 110,
      "hex": "D14",
      "tile": "6-2",
      "type": "lay_tile",
      "entity": "NYC",
      "rotation": 3,
      "entity_type": "corporation",
      "original_id": 162
    },
    {
      "id": 111,
      "hex": "B14",
      "tile": "7-2",
      "type": "lay_tile",
      "entity": "NYC",
      "rotation": 4,
      "entity_type": "corporation",
      "original_id": 163
    },
    {
      "id": 112,
      "city": "295-0-0",
      "slot": 1,
      "type": "place_token",
      "entity": "NYC",
      "entity_type": "corporation",
      "original_id": 164
    },
    {
      "id": 113,
      "type": "run_routes",
      "entity": "NYC",
      "routes": [
        {
          "train": "2-2",
          "connections": [
            [
              "B16",
              "C15"
            ]
          ]
        },
        {
          "train": "2-3",
          "connections": [
            [
              "E17",
              "E19",
              "D20"
            ]
          ]
        }
      ],
      "entity_type": "corporation",
      "original_id": 165
    },
    {
      "id": 114,
      "kind": "payout",
      "type": "dividend",
      "entity": "NYC",
      "entity_type": "corporation",
      "original_id": 166
    },
    {
      "id": 115,
      "type": "buy_train",
      "price": 180,
      "train": "4-2",
      "entity": "NYC",
      "variant": "4",
      "entity_type": "corporation",
      "original_id": 167
    },
    {
      "id": 116,
      "type": "pass",
      "entity": "NYC",
      "entity_type": "corporation",
      "original_id": 168
    },
    {
      "id": 117,
      "type": "pass",
      "entity": "IC",
      "entity_type": "corporation",
      "original_id": 169
    },
    {
      "id": 118,
      "hex": "D6",
      "tile": "298-0",
      "type": "lay_tile",
      "entity": "IC",
      "rotation": 0,
      "entity_type": "corporation",
      "original_id": 170
    },
    {
      "id": 119,
      "type": "pass",
      "entity": "IC",
      "entity_type": "corporation",
      "original_id": 171
    },
    {
      "id": 120,
      "type": "run_routes",
      "entity": "IC",
      "routes": [
        {
          "train": "2-4",
          "connections": [
            [
              "B16",
              "C15"
            ]
          ]
        },
        {
          "train": "2-5",
          "connections": [
            [
              "I5",
              "I3",
              "I1"
            ]
          ]
        },
        {
          "train": "4-1",
          "connections": [
            [
              "E17",
              "E19",
              "D20"
            ],
            [
              "E17",
              "E15",
              "D14"
            ],
            [
              "C15",
              "D14"
            ]
          ]
        },
        {
          "train": "2-0",
          "connections": [
            [
              "C15",
              "C13",
              "D12",
              "D10",
              "E9",
              "E7",
              "D6"
            ]
          ]
        }
      ],
      "entity_type": "corporation",
      "original_id": 172
    },
    {
      "id": 121,
      "kind": "payout",
      "type": "dividend",
      "entity": "IC",
      "entity_type": "corporation",
      "original_id": 183
    },
    {
      "id": 122,
      "type": "buy_shares",
      "entity": "GT",
      "shares": [
        "GT_3"
      ],
      "entity_type": "corporation",
      "share_price": 90,
      "original_id": 184
    },
    {
      "id": 123,
      "hex": "H6",
      "tile": "26-0",
      "type": "lay_tile",
      "entity": "GT",
      "rotation": 3,
      "entity_type": "corporation",
      "original_id": 185
    },
    {
      "id": 124,
      "type": "assign",
      "entity": "MPC",
      "target": "I1",
      "entity_type": "company",
      "target_type": "hex",
      "original_id": 186
    },
    {
      "id": 125,
      "type": "pass",
      "entity": "GT",
      "entity_type": "corporation",
      "original_id": 189
    },
    {
      "id": 126,
      "type": "run_routes",
      "entity": "GT",
      "routes": [
        {
          "train": "2-6",
          "connections": [
            [
              "B16",
              "C15"
            ]
          ]
        },
        {
          "train": "4-0",
          "connections": [
            [
              "I5",
              "I3",
              "I1"
            ],
            [
              "I5",
              "H6",
              "G7"
            ],
            [
              "G9",
              "G7"
            ]
          ]
        },
        {
          "train": "2-1",
          "connections": [
            [
              "G9",
              "G11",
              "H12"
            ]
          ]
        }
      ],
      "entity_type": "corporation",
      "original_id": 190
    },
    {
      "id": 127,
      "kind": "payout",
      "type": "dividend",
      "entity": "GT",
      "entity_type": "corporation",
      "original_id": 191
    },
    {
      "id": 128,
      "type": "buy_train",
      "price": 160,
      "train": "4-3",
      "entity": "GT",
      "variant": "3/5",
      "entity_type": "corporation",
      "original_id": 192
    },
    {
      "id": 129,
      "type": "pass",
      "entity": "IC",
      "entity_type": "corporation",
      "original_id": 193
    },
    {
      "id": 130,
      "hex": "B16",
      "tile": "619-0",
      "type": "lay_tile",
      "entity": "IC",
      "rotation": 4,
      "entity_type": "corporation",
      "original_id": 194
    },
    {
      "id": 131,
      "type": "message",
      "entity": "Saintis",
      "message": "a lol should have gotten a 3/5 instead lol",
      "entity_type": "player",
      "original_id": 196
    },
    {
      "id": 132,
      "city": "293-0-0",
      "slot": 0,
      "type": "place_token",
      "entity": "IC",
      "entity_type": "corporation",
      "original_id": 206
    },
    {
      "id": 133,
      "type": "pass",
      "entity": "IC",
      "entity_type": "corporation",
      "original_id": 207
    },
    {
      "id": 134,
      "type": "run_routes",
      "entity": "IC",
      "routes": [
        {
          "train": "2-4",
          "connections": [
            [
              "C15",
              "D14"
            ]
          ]
        },
        {
          "train": "2-5",
          "connections": [
            [
              "E17",
              "E19",
              "D20"
            ]
          ]
        },
        {
          "train": "4-1",
          "connections": [
            [
              "C5",
              "D6"
            ],
            [
              "C15",
              "C13",
              "D12",
              "D10",
              "E9",
              "E7",
              "D6"
            ],
            [
              "C15",
              "B16"
            ],
            [
              "B18",
              "B16"
            ]
          ]
        },
        {
          "train": "2-0",
          "connections": [
            [
              "C15",
              "B14",
              "B16"
            ]
          ]
        }
      ],
      "entity_type": "corporation",
      "original_id": 208
    },
    {
      "id": 135,
      "kind": "payout",
      "type": "dividend",
      "entity": "IC",
      "entity_type": "corporation",
      "original_id": 209
    },
    {
      "id": 136,
      "type": "sell_shares",
      "entity": "NYC",
      "shares": [
        "NYC_4",
        "NYC_5"
      ],
      "percent": 20,
      "entity_type": "corporation",
      "share_price": 90,
      "original_id": 222
    },
    {
      "id": 137,
      "type": "pass",
      "entity": "NYC",
      "entity_type": "corporation",
      "original_id": 223
    },
    {
      "id": 138,
      "type": "run_routes",
      "entity": "NYC",
      "routes": [
        {
          "train": "2-2",
          "connections": [
            [
              "C15",
              "B16"
            ]
          ]
        },
        {
          "train": "2-3",
          "connections": [
            [
              "E17",
              "E19",
              "D20"
            ]
          ]
        },
        {
          "train": "4-2",
          "connections": [
            [
              "B18",
              "B16"
            ],
            [
              "C15",
              "B14",
              "B16"
            ],
            [
              "C15",
              "C13",
              "D12",
              "D10",
              "E9",
              "D8",
              "D6"
            ]
          ]
        }
      ],
      "entity_type": "corporation",
      "original_id": 224
    },
    {
      "id": 139,
      "kind": "withhold",
      "type": "dividend",
      "entity": "NYC",
      "entity_type": "corporation",
      "original_id": 225
    },
    {
      "id": 140,
      "type": "buy_train",
      "price": 500,
      "train": "5-0",
      "entity": "NYC",
      "variant": "5",
      "entity_type": "corporation",
      "original_id": 226
    },
    {
      "id": 141,
      "type": "pass",
      "entity": "NYC",
      "entity_type": "corporation",
      "original_id": 227
    },
    {
      "id": 142,
      "type": "sell_shares",
      "entity": "GT",
      "shares": [
        "GT_5"
      ],
      "percent": 10,
      "entity_type": "corporation",
      "share_price": 90,
      "original_id": 228
    },
    {
      "id": 143,
      "hex": "C15",
      "tile": "297-0",
      "type": "lay_tile",
      "entity": "GT",
      "rotation": 0,
      "entity_type": "corporation",
      "original_id": 229
    },
    {
      "id": 144,
      "type": "pass",
      "entity": "GT",
      "entity_type": "corporation",
      "original_id": 230
    },
    {
      "id": 145,
      "type": "run_routes",
      "entity": "GT",
      "routes": [
        {
          "train": "2-6",
          "connections": [
            [
              "B16",
              "C15"
            ]
          ]
        },
        {
          "train": "4-0",
          "connections": [
            [
              "C5",
              "D6"
            ],
            [
              "D6",
              "D8",
              "E9",
              "D10",
              "D12",
              "C13",
              "C15"
            ],
            [
              "B16",
              "B14",
              "C15"
            ],
            [
              "B18",
              "B16"
            ]
          ]
        },
        {
          "train": "2-1",
          "connections": [
            [
              "G9",
              "G11",
              "H12"
            ]
          ]
        },
        {
          "train": "4-3",
          "connections": [
            [
              "I5",
              "I3",
              "I1"
            ],
            [
              "I5",
              "H6",
              "G7"
            ],
            [
              "G9",
              "G7"
            ]
          ]
        }
      ],
      "entity_type": "corporation",
      "original_id": 231
    },
    {
      "id": 146,
      "kind": "half",
      "type": "dividend",
      "entity": "GT",
      "entity_type": "corporation",
      "original_id": 232
    },
    {
      "id": 147,
      "type": "pass",
      "entity": "GT",
      "entity_type": "corporation",
      "original_id": 233
    },
    {
      "id": 148,
      "type": "buy_shares",
      "entity": "Saintis",
      "shares": [
        "NYC_4"
      ],
      "entity_type": "player",
      "original_id": 234
    },
    {
      "id": 149,
      "type": "buy_shares",
      "entity": "tomdidiot",
      "shares": [
        "NYC_6"
      ],
      "entity_type": "player",
      "original_id": 235
    },
    {
      "id": 150,
      "type": "buy_shares",
      "entity": "steak",
      "shares": [
        "NYC_7"
      ],
      "entity_type": "player",
      "original_id": 236
    },
    {
      "id": 151,
      "type": "buy_shares",
      "entity": "Saintis",
      "shares": [
        "NYC_5"
      ],
      "entity_type": "player",
      "original_id": 237
    },
    {
      "id": 152,
      "type": "buy_shares",
      "entity": "tomdidiot",
      "shares": [
        "NYC_8"
      ],
      "entity_type": "player",
      "original_id": 240
    },
    {
      "id": 153,
      "type": "buy_shares",
      "entity": "steak",
      "shares": [
        "GT_5"
      ],
      "entity_type": "player",
      "original_id": 241
    },
    {
      "id": 154,
      "type": "pass",
      "entity": "Saintis",
      "entity_type": "player",
      "original_id": 242
    },
    {
      "id": 155,
      "type": "buy_shares",
      "entity": "tomdidiot",
      "shares": [
        "IC_5"
      ],
      "entity_type": "player",
      "original_id": 243
    },
    {
      "id": 156,
      "type": "pass",
      "entity": "steak",
      "entity_type": "player",
      "original_id": 244
    },
    {
      "id": 157,
      "type": "pass",
      "entity": "Saintis",
      "entity_type": "player",
      "original_id": 245
    },
    {
      "id": 158,
      "type": "pass",
      "entity": "tomdidiot",
      "entity_type": "player",
      "original_id": 246
    },
    {
      "id": 159,
      "type": "pass",
      "entity": "IC",
      "entity_type": "corporation",
      "original_id": 247
    },
    {
      "id": 160,
      "hex": "D6",
      "tile": "299-0",
      "type": "lay_tile",
      "entity": "IC",
      "rotation": 0,
      "entity_type": "corporation",
      "original_id": 248
    },
    {
      "id": 161,
      "type": "pass",
      "entity": "IC",
      "entity_type": "corporation",
      "original_id": 249
    },
    {
      "id": 162,
      "type": "run_routes",
      "entity": "IC",
      "routes": [
        {
          "train": "2-4",
          "connections": [
            [
              "D14",
              "C15"
            ]
          ]
        },
        {
          "train": "2-5",
          "connections": [
            [
              "B16",
              "B14",
              "C15"
            ]
          ]
        },
        {
          "train": "4-1",
          "connections": [
            [
              "C17",
              "C15"
            ],
            [
              "C15",
              "C13",
              "D12",
              "D10",
              "E9",
              "E7",
              "D6"
            ],
            [
              "C5",
              "D6"
            ]
          ]
        },
        {
          "train": "2-0",
          "connections": [
            [
              "B16",
              "C15"
            ]
          ]
        }
      ],
      "entity_type": "corporation",
      "original_id": 254
    },
    {
      "id": 163,
      "kind": "payout",
      "type": "dividend",
      "entity": "IC",
      "entity_type": "corporation",
      "original_id": 257
    },
    {
      "id": 164,
      "type": "buy_train",
      "price": 500,
      "train": "5-1",
      "entity": "IC",
      "variant": "5",
      "entity_type": "corporation",
      "original_id": 258
    },
    {
      "id": 165,
      "type": "pass",
      "entity": "IC",
      "entity_type": "corporation",
      "original_id": 259
    },
    {
      "id": 166,
      "type": "pass",
      "entity": "GT",
      "entity_type": "corporation",
      "original_id": 280
    },
    {
      "id": 167,
      "hex": "H12",
      "tile": "296-0",
      "type": "lay_tile",
      "entity": "GT",
      "rotation": 0,
      "entity_type": "corporation",
      "original_id": 281
    },
    {
      "id": 168,
      "type": "pass",
      "entity": "GT",
      "entity_type": "corporation",
      "original_id": 282
    },
    {
      "id": 169,
      "type": "run_routes",
      "entity": "GT",
      "routes": [
        {
          "train": "4-0",
          "connections": [
            [
              "C5",
              "D6"
            ],
            [
              "C15",
              "C13",
              "D12",
              "D10",
              "E9",
              "D8",
              "D6"
            ],
            [
              "B16",
              "C15"
            ],
            [
              "B18",
              "B16"
            ]
          ]
        },
        {
          "train": "4-3",
          "connections": [
            [
              "I5",
              "I3",
              "I1"
            ],
            [
              "I5",
              "H6",
              "G7"
            ],
            [
              "G9",
              "G7"
            ],
            [
              "G9",
              "G11",
              "H12"
            ]
          ]
        }
      ],
      "entity_type": "corporation",
      "original_id": 283
    },
    {
      "id": 170,
      "kind": "payout",
      "type": "dividend",
      "entity": "GT",
      "entity_type": "corporation",
      "original_id": 284
    },
    {
      "id": 171,
      "type": "buy_train",
      "price": 450,
      "train": "5-2",
      "entity": "GT",
      "variant": "4/6",
      "entity_type": "corporation",
      "original_id": 285
    },
    {
      "id": 172,
      "hex": "E17",
      "tile": "294-0",
      "type": "lay_tile",
      "entity": "NYC",
      "rotation": 0,
      "entity_type": "corporation",
      "original_id": 286
    },
    {
      "id": 173,
      "hex": "D18",
      "tile": "8-8",
      "type": "lay_tile",
      "entity": "NYC",
      "rotation": 4,
      "entity_type": "corporation",
      "original_id": 287
    },
    {
      "id": 174,
      "city": "294-0-0",
      "slot": 1,
      "type": "place_token",
      "entity": "NYC",
      "entity_type": "corporation",
      "original_id": 288
    },
    {
      "id": 175,
      "type": "run_routes",
      "entity": "NYC",
      "routes": [
        {
          "train": "2-2",
          "connections": [
            [
              "C21",
              "D20"
            ]
          ]
        },
        {
          "train": "2-3",
          "connections": [
            [
              "D22",
              "D20"
            ]
          ]
        },
        {
          "train": "4-2",
          "connections": [
            [
              "C17",
              "C15"
            ],
            [
              "C15",
              "C13",
              "D12",
              "D10",
              "E9",
              "D8",
              "D6"
            ],
            [
              "C5",
              "D6"
            ]
          ]
        },
        {
          "train": "5-0",
          "connections": [
            [
              "D14",
              "E15",
              "E17"
            ],
            [
              "D14",
              "C15"
            ],
            [
              "B16",
              "C15"
            ],
            [
              "B18",
              "B16"
            ]
          ]
        }
      ],
      "entity_type": "corporation",
      "original_id": 289
    },
    {
      "id": 176,
      "kind": "half",
      "type": "dividend",
      "entity": "NYC",
      "entity_type": "corporation",
      "original_id": 290
    },
    {
      "id": 177,
      "type": "pass",
      "entity": "NYC",
      "entity_type": "corporation",
      "original_id": 291
    },
    {
      "id": 178,
      "type": "pass",
      "entity": "IC",
      "entity_type": "corporation",
      "original_id": 292
    },
    {
      "id": 179,
      "hex": "E17",
      "tile": "297-1",
      "type": "lay_tile",
      "entity": "IC",
      "rotation": 3,
      "entity_type": "corporation",
      "original_id": 293
    },
    {
      "id": 180,
      "hex": "F16",
      "tile": "8-9",
      "type": "lay_tile",
      "entity": "IC",
      "rotation": 1,
      "entity_type": "corporation",
      "original_id": 300
    },
    {
      "id": 181,
      "type": "pass",
      "entity": "IC",
      "entity_type": "corporation",
      "original_id": 301
    },
    {
      "id": 182,
      "type": "run_routes",
      "entity": "IC",
      "routes": [
        {
          "train": "4-1",
          "connections": [
            [
              "D14",
              "E15",
              "E17"
            ],
            [
              "D14",
              "C15"
            ],
            [
              "C17",
              "C15"
            ]
          ]
        },
        {
          "train": "5-1",
          "connections": [
            [
              "B18",
              "B16"
            ],
            [
              "B16",
              "C15"
            ],
            [
              "C15",
              "C13",
              "D12",
              "D10",
              "E9",
              "E7",
              "D6"
            ],
            [
              "C5",
              "D6"
            ]
          ]
        }
      ],
      "entity_type": "corporation",
      "original_id": 302
    },
    {
      "id": 183,
      "kind": "payout",
      "type": "dividend",
      "entity": "IC",
      "entity_type": "corporation",
      "original_id": 303
    },
    {
      "id": 184,
      "type": "pass",
      "entity": "IC",
      "entity_type": "corporation",
      "original_id": 304
    },
    {
      "id": 185,
      "type": "sell_shares",
      "entity": "GT",
      "shares": [
        "GT_6"
      ],
      "percent": 10,
      "entity_type": "corporation",
      "share_price": 137,
      "original_id": 307
    },
    {
      "id": 186,
      "city": "297-0-0",
      "slot": 2,
      "type": "place_token",
      "entity": "GT",
      "entity_type": "corporation",
      "original_id": 312
    },
    {
      "id": 187,
      "hex": "D8",
      "tile": "24-0",
      "type": "lay_tile",
      "entity": "GT",
      "rotation": 5,
      "entity_type": "corporation",
      "original_id": 321
    },
    {
      "id": 188,
      "type": "pass",
      "entity": "GT",
      "entity_type": "corporation",
      "original_id": 322
    },
    {
      "id": 189,
      "type": "run_routes",
      "entity": "GT",
      "routes": [
        {
          "train": "4-0",
          "connections": [
            [
              "I5",
              "I3",
              "I1"
            ],
            [
              "I5",
              "H6",
              "G7"
            ],
            [
              "G9",
              "G7"
            ],
            [
              "G9",
              "G11",
              "H12"
            ]
          ]
        },
        {
          "train": "4-3",
          "connections": [
            [
              "D22",
              "D20"
            ],
            [
              "D20",
              "E19",
              "E17"
            ],
            [
              "D14",
              "E15",
              "E17"
            ],
            [
              "D14",
              "C15"
            ]
          ]
        },
        {
          "train": "5-2",
          "connections": [
            [
              "C5",
              "D6"
            ],
            [
              "D6",
              "D8",
              "E9",
              "D10",
              "D12",
              "C13",
              "C15"
            ],
            [
              "C17",
              "C15"
            ]
          ]
        }
      ],
      "entity_type": "corporation",
      "original_id": 323
    },
    {
      "id": 190,
      "kind": "half",
      "type": "dividend",
      "entity": "GT",
      "entity_type": "corporation",
      "original_id": 324
    },
    {
      "id": 191,
      "type": "pass",
      "entity": "NYC",
      "entity_type": "corporation",
      "original_id": 333
    },
    {
      "id": 192,
      "type": "run_routes",
      "entity": "NYC",
      "routes": [
        {
          "train": "4-2",
          "connections": [
            [
              "C17",
              "C15"
            ],
            [
              "D6",
              "D8",
              "E9",
              "D10",
              "D12",
              "C13",
              "C15"
            ],
            [
              "C5",
              "D6"
            ]
          ]
        },
        {
          "train": "5-0",
          "connections": [
            [
              "D22",
              "D20"
            ],
            [
              "D20",
              "E19",
              "E17"
            ],
            [
              "D14",
              "E15",
              "E17"
            ],
            [
              "D14",
              "C15"
            ]
          ]
        }
      ],
      "entity_type": "corporation",
      "original_id": 334
    },
    {
      "id": 193,
      "kind": "half",
      "type": "dividend",
      "entity": "NYC",
      "entity_type": "corporation",
      "original_id": 335
    },
    {
      "id": 194,
      "type": "buy_train",
      "price": 800,
      "train": "6-0",
      "entity": "NYC",
      "variant": "6",
      "entity_type": "corporation",
      "original_id": 336
    },
    {
      "id": 195,
      "type": "buy_shares",
      "entity": "steak",
      "shares": [
        "IC_6"
      ],
      "entity_type": "player",
      "original_id": 337
    },
    {
      "id": 196,
      "type": "buy_shares",
      "entity": "Saintis",
      "shares": [
        "IC_7"
      ],
      "entity_type": "player",
      "original_id": 338
    },
    {
      "id": 197,
      "type": "buy_shares",
      "entity": "tomdidiot",
      "shares": [
        "IC_8"
      ],
      "entity_type": "player",
      "original_id": 339
    },
    {
      "id": 198,
      "type": "buy_shares",
      "entity": "steak",
      "shares": [
        "GT_6"
      ],
      "entity_type": "player",
      "original_id": 340
    },
    {
      "id": 199,
      "type": "buy_shares",
      "entity": "Saintis",
      "shares": [
        "GT_7"
      ],
      "entity_type": "player",
      "original_id": 341
    },
    {
      "id": 200,
      "type": "buy_shares",
      "entity": "tomdidiot",
      "shares": [
        "GT_8"
      ],
      "entity_type": "player",
      "original_id": 342
    },
    {
      "id": 201,
      "type": "pass",
      "entity": "steak",
      "entity_type": "player",
      "original_id": 343
    },
    {
      "id": 202,
      "type": "pass",
      "entity": "Saintis",
      "entity_type": "player",
      "original_id": 344
    },
    {
      "id": 203,
      "type": "buy_shares",
      "entity": "tomdidiot",
      "shares": [
        "GT_3"
      ],
      "entity_type": "player",
      "original_id": 345
    },
    {
      "id": 204,
      "type": "pass",
      "entity": "steak",
      "entity_type": "player",
      "original_id": 346
    },
    {
      "id": 205,
      "type": "pass",
      "entity": "Saintis",
      "entity_type": "player",
      "original_id": 347
    },
    {
      "id": 206,
      "type": "pass",
      "entity": "tomdidiot",
      "entity_type": "player",
      "original_id": 348
    },
    {
      "id": 207,
      "hex": "C15",
      "tile": "290-0",
      "type": "lay_tile",
      "entity": "IC",
      "rotation": 0,
      "entity_type": "corporation",
      "original_id": 349
    },
    {
      "id": 208,
      "type": "pass",
      "entity": "IC",
      "entity_type": "corporation",
      "original_id": 350
    },
    {
      "id": 209,
      "type": "run_routes",
      "entity": "IC",
      "routes": [
        {
          "train": "4-1",
          "connections": [
            [
              "D14",
              "E15",
              "E17"
            ],
            [
              "D14",
              "C15"
            ],
            [
              "C17",
              "C15"
            ]
          ]
        },
        {
          "train": "5-1",
          "connections": [
            [
              "B18",
              "B16"
            ],
            [
              "B16",
              "C15"
            ],
            [
              "D6",
              "E7",
              "E9",
              "D10",
              "D12",
              "C13",
              "C15"
            ],
            [
              "C5",
              "D6"
            ]
          ]
        }
      ],
      "entity_type": "corporation",
      "original_id": 351
    },
    {
      "id": 210,
      "kind": "half",
      "type": "dividend",
      "entity": "IC",
      "entity_type": "corporation",
      "original_id": 352
    },
    {
      "id": 211,
      "type": "buy_train",
      "price": 900,
      "train": "6-1",
      "entity": "IC",
      "variant": "7/8",
      "entity_type": "corporation",
      "original_id": 353
    },
    {
      "id": 212,
      "hex": "H12",
      "tile": "297-0",
      "type": "lay_tile",
      "entity": "GT",
      "rotation": 0,
      "entity_type": "corporation",
      "original_id": 354
    },
    {
      "id": 213,
      "hex": "G13",
      "tile": "57-1",
      "type": "lay_tile",
      "entity": "GT",
      "rotation": 0,
      "entity_type": "corporation",
      "original_id": 357
    },
    {
      "id": 214,
      "type": "pass",
      "entity": "GT",
      "entity_type": "corporation",
      "original_id": 358
    },
    {
      "id": 215,
      "type": "run_routes",
      "entity": "GT",
      "routes": [
        {
          "train": "4-0",
          "connections": [
            [
              "D22",
              "D20"
            ],
            [
              "D20",
              "E19",
              "E17"
            ],
            [
              "D14",
              "E15",
              "E17"
            ],
            [
              "D14",
              "C15"
            ]
          ]
        },
        {
          "train": "4-3",
          "connections": [
            [
              "I5",
              "I3",
              "I1"
            ],
            [
              "I5",
              "H6",
              "G7"
            ],
            [
              "G9",
              "G7"
            ],
            [
              "G9",
              "G11",
              "H12"
            ]
          ]
        },
        {
          "train": "5-2",
          "connections": [
            [
              "C5",
              "D6"
            ],
            [
              "D6",
              "D8",
              "E9",
              "D10",
              "D12",
              "C13",
              "C15"
            ],
            [
              "C17",
              "C15"
            ]
          ]
        }
      ],
      "entity_type": "corporation",
      "original_id": 359
    },
    {
      "id": 216,
      "kind": "payout",
      "type": "dividend",
      "entity": "GT",
      "entity_type": "corporation",
      "original_id": 360
    },
    {
      "id": 217,
      "type": "buy_train",
      "price": 900,
      "train": "6-2",
      "entity": "GT",
      "variant": "7/8",
      "entity_type": "corporation",
      "original_id": 361
    },
    {
      "id": 218,
      "type": "run_routes",
      "entity": "NYC",
      "routes": [
        {
          "train": "4-2",
          "connections": [
            [
              "C17",
              "C15"
            ],
            [
              "D6",
              "D8",
              "E9",
              "D10",
              "D12",
              "C13",
              "C15"
            ],
            [
              "C5",
              "D6"
            ]
          ]
        },
        {
          "train": "5-0",
          "connections": [
            [
              "D20",
              "D18",
              "E17"
            ],
            [
              "C21",
              "D20"
            ]
          ]
        },
        {
          "train": "6-0",
          "connections": [
            [
              "D22",
              "D20"
            ],
            [
              "D20",
              "E19",
              "E17"
            ],
            [
              "D14",
              "E15",
              "E17"
            ],
            [
              "D14",
              "C15"
            ],
            [
              "B16",
              "C15"
            ]
          ]
        }
      ],
      "entity_type": "corporation",
      "original_id": 362
    },
    {
      "id": 219,
      "kind": "half",
      "type": "dividend",
      "entity": "NYC",
      "entity_type": "corporation",
      "original_id": 363
    },
    {
      "id": 220,
      "hex": "F14",
      "tile": "8-10",
      "type": "lay_tile",
      "entity": "IC",
      "rotation": 4,
      "entity_type": "corporation",
      "original_id": 364
    },
    {
      "id": 221,
      "hex": "H10",
      "tile": "8-11",
      "type": "lay_tile",
      "entity": "IC",
      "rotation": 4,
      "entity_type": "corporation",
      "original_id": 369
    },
    {
      "id": 222,
      "city": "297-0-0",
      "slot": 1,
      "type": "place_token",
      "entity": "IC",
      "entity_type": "corporation",
      "original_id": 370
    },
    {
      "id": 223,
      "type": "run_routes",
      "entity": "IC",
      "routes": [
        {
          "train": "5-1",
          "connections": [
            [
              "B18",
              "B16"
            ],
            [
              "B16",
              "C15"
            ],
            [
              "D6",
              "E7",
              "E9",
              "D10",
              "D12",
              "C13",
              "C15"
            ],
            [
              "C5",
              "D6"
            ]
          ]
        },
        {
          "train": "6-1",
          "connections": [
            [
              "G9",
              "G11",
              "H12"
            ],
            [
              "H12",
              "G13"
            ],
            [
              "G13",
              "F14",
              "F16",
              "E17"
            ],
            [
              "D14",
              "E15",
              "E17"
            ],
            [
              "D14",
              "C15"
            ],
            [
              "C17",
              "C15"
            ]
          ]
        }
      ],
      "entity_type": "corporation",
      "original_id": 371
    },
    {
      "id": 224,
      "kind": "payout",
      "type": "dividend",
      "entity": "IC",
      "entity_type": "corporation",
      "original_id": 372
    },
    {
      "id": 225,
      "hex": "I9",
      "tile": "8-12",
      "type": "lay_tile",
      "entity": "GT",
      "rotation": 3,
      "entity_type": "corporation",
      "original_id": 373
    },
    {
      "id": 226,
      "city": "297-1-0",
      "slot": 2,
      "type": "place_token",
      "entity": "GT",
      "entity_type": "corporation",
      "original_id": 374
    },
    {
      "type": "pass",
      "entity": "GT",
      "entity_type": "corporation",
      "original_id": null,
      "id": 227
    },
    {
      "id": 228,
      "type": "run_routes",
      "entity": "GT",
      "routes": [
        {
          "train": "5-2",
          "connections": [
            [
              "C5",
              "D6"
            ],
            [
              "D6",
              "D8",
              "E9",
              "D10",
              "D12",
              "C13",
              "C15"
            ],
            [
              "C17",
              "C15"
            ]
          ]
        },
        {
          "train": "6-2",
          "connections": [
            [
              "J10",
              "I9",
              "H10",
              "H12"
            ],
            [
              "H12",
              "G13"
            ],
            [
              "G13",
              "F14",
              "F16",
              "E17"
            ],
            [
              "D14",
              "E15",
              "E17"
            ],
            [
              "D14",
              "C15"
            ],
            [
              "B16",
              "C15"
            ],
            [
              "B18",
              "B16"
            ]
          ]
        }
      ],
      "entity_type": "corporation",
      "original_id": 375
    },
    {
      "id": 229,
      "kind": "payout",
      "type": "dividend",
      "entity": "GT",
      "entity_type": "corporation",
      "original_id": 376
    },
    {
      "id": 230,
      "hex": "H10",
      "tile": "24-1",
      "type": "lay_tile",
      "entity": "NYC",
      "rotation": 4,
      "entity_type": "corporation",
      "original_id": 379
    },
    {
      "id": 231,
      "hex": "H8",
      "tile": "9-2",
      "type": "lay_tile",
      "entity": "NYC",
      "rotation": 1,
      "entity_type": "corporation",
      "original_id": 380
    },
    {
      "id": 232,
      "type": "pass",
      "entity": "NYC",
      "entity_type": "corporation",
      "original_id": 381
    },
    {
      "id": 233,
      "type": "run_routes",
      "entity": "NYC",
      "routes": [
        {
          "train": "5-0",
          "connections": [
            [
              "B18",
              "B16"
            ],
            [
              "B16",
              "C15"
            ],
            [
              "D6",
              "D8",
              "E9",
              "D10",
              "D12",
              "C13",
              "C15"
            ],
            [
              "C5",
              "D6"
            ]
          ]
        },
        {
          "train": "6-0",
          "connections": [
            [
              "J10",
              "I9",
              "H10",
              "H12"
            ],
            [
              "H12",
              "G13"
            ],
            [
              "G13",
              "F14",
              "F16",
              "E17"
            ],
            [
              "D20",
              "D18",
              "E17"
            ],
            [
              "D22",
              "D20"
            ]
          ]
        }
      ],
      "entity_type": "corporation",
      "original_id": 382
    },
    {
      "id": 234,
      "kind": "payout",
      "type": "dividend",
      "entity": "NYC",
      "entity_type": "corporation",
      "original_id": 383
    },
    {
      "id": 235,
      "type": "par",
      "entity": "steak",
      "corporation": "B&O",
      "entity_type": "player",
      "share_price": "150,0,14",
      "original_id": 384
    },
    {
      "id": 236,
      "type": "buy_shares",
      "entity": "Saintis",
      "shares": [
        "B&O_1"
      ],
      "entity_type": "player",
      "original_id": 385
    },
    {
      "id": 237,
      "type": "par",
      "entity": "tomdidiot",
      "corporation": "ERIE",
      "entity_type": "player",
      "share_price": "150,0,14",
      "original_id": 386
    },
    {
      "id": 238,
      "type": "buy_shares",
      "entity": "steak",
      "shares": [
        "B&O_2"
      ],
      "entity_type": "player",
      "original_id": 387
    },
    {
      "id": 239,
      "type": "buy_shares",
      "entity": "Saintis",
      "shares": [
        "B&O_3"
      ],
      "entity_type": "player",
      "original_id": 388
    },
    {
      "id": 240,
      "type": "buy_shares",
      "entity": "tomdidiot",
      "shares": [
        "ERIE_1"
      ],
      "entity_type": "player",
      "original_id": 389
    },
    {
      "id": 241,
      "type": "buy_shares",
      "entity": "steak",
      "shares": [
        "B&O_4"
      ],
      "entity_type": "player",
      "original_id": 390
    },
    {
      "id": 242,
      "type": "buy_shares",
      "entity": "Saintis",
      "shares": [
        "B&O_5"
      ],
      "entity_type": "player",
      "original_id": 391
    },
    {
      "id": 243,
      "type": "buy_shares",
      "entity": "tomdidiot",
      "shares": [
        "ERIE_2"
      ],
      "entity_type": "player",
      "original_id": 392
    },
    {
      "id": 244,
      "type": "buy_shares",
      "entity": "steak",
      "shares": [
        "B&O_6"
      ],
      "entity_type": "player",
      "original_id": 393
    },
    {
      "id": 245,
      "type": "buy_shares",
      "entity": "Saintis",
      "shares": [
        "B&O_7"
      ],
      "entity_type": "player",
      "original_id": 394
    },
    {
      "id": 246,
      "type": "buy_shares",
      "entity": "tomdidiot",
      "shares": [
        "ERIE_3"
      ],
      "entity_type": "player",
      "original_id": 395
    },
    {
      "id": 247,
      "type": "buy_shares",
      "entity": "steak",
      "shares": [
        "B&O_8"
      ],
      "entity_type": "player",
      "original_id": 396
    },
    {
      "id": 248,
      "type": "buy_shares",
      "entity": "Saintis",
      "shares": [
        "ERIE_4"
      ],
      "entity_type": "player",
      "original_id": 397
    },
    {
      "id": 249,
      "type": "pass",
      "entity": "tomdidiot",
      "entity_type": "player",
      "original_id": 398
    },
    {
      "id": 250,
      "type": "pass",
      "entity": "steak",
      "entity_type": "player",
      "original_id": 399
    },
    {
      "id": 251,
      "type": "buy_shares",
      "entity": "Saintis",
      "shares": [
        "ERIE_5"
      ],
      "entity_type": "player",
      "original_id": 400
    },
    {
      "id": 252,
      "type": "pass",
      "entity": "tomdidiot",
      "entity_type": "player",
      "original_id": 401
    },
    {
      "id": 253,
      "type": "pass",
      "entity": "steak",
      "entity_type": "player",
      "original_id": 402
    },
    {
      "id": 254,
      "type": "pass",
      "entity": "Saintis",
      "entity_type": "player",
      "original_id": 403
    },
    {
      "id": 255,
      "hex": "I7",
      "tile": "9-3",
      "type": "lay_tile",
      "entity": "IC",
      "rotation": 1,
      "entity_type": "corporation",
      "original_id": 404
    },
    {
      "id": 256,
      "hex": "I9",
      "tile": "25-0",
      "type": "lay_tile",
      "entity": "IC",
      "rotation": 3,
      "entity_type": "corporation",
      "original_id": 405
    },
    {
      "id": 257,
      "type": "run_routes",
      "entity": "IC",
      "routes": [
        {
          "train": "5-1",
          "connections": [
            [
              "B18",
              "B16"
            ],
            [
              "B16",
              "C15"
            ],
            [
              "D6",
              "E7",
              "E9",
              "D10",
              "D12",
              "C13",
              "C15"
            ],
            [
              "C5",
              "D6"
            ]
          ]
        },
        {
          "train": "6-1",
          "connections": [
            [
              "I5",
              "I3",
              "I1"
            ],
            [
              "I5",
              "I7",
              "I9",
              "H10",
              "H12"
            ],
            [
              "H12",
              "G13"
            ],
            [
              "G13",
              "F14",
              "F16",
              "E17"
            ],
            [
              "D14",
              "E15",
              "E17"
            ],
            [
              "D14",
              "C15"
            ],
            [
              "C17",
              "C15"
            ]
          ]
        }
      ],
      "entity_type": "corporation",
      "original_id": 406
    },
    {
      "id": 258,
      "kind": "payout",
      "type": "dividend",
      "entity": "IC",
      "entity_type": "corporation",
      "original_id": 407
    },
    {
      "id": 259,
      "type": "run_routes",
      "entity": "GT",
      "routes": [
        {
          "train": "5-2",
          "connections": [
            [
              "C5",
              "D6"
            ],
            [
              "D6",
              "D8",
              "E9",
              "D10",
              "D12",
              "C13",
              "C15"
            ],
            [
              "C17",
              "C15"
            ]
          ]
        },
        {
          "train": "6-2",
          "connections": [
            [
              "D22",
              "D20"
            ],
            [
              "D20",
              "E19",
              "E17"
            ],
            [
              "G13",
              "F14",
              "F16",
              "E17"
            ],
            [
              "H12",
              "G13"
            ],
            [
              "I5",
              "I7",
              "I9",
              "H10",
              "H12"
            ],
            [
              "I5",
              "I3",
              "I1"
            ]
          ]
        }
      ],
      "entity_type": "corporation",
      "original_id": 408
    },
    {
      "id": 260,
      "kind": "payout",
      "type": "dividend",
      "entity": "GT",
      "entity_type": "corporation",
      "original_id": 409
    },
    {
      "id": 261,
      "hex": "E19",
      "tile": "30-0",
      "type": "lay_tile",
      "entity": "NYC",
      "rotation": 3,
      "entity_type": "corporation",
      "original_id": 410
    },
    {
      "id": 262,
      "city": "297-0-0",
      "slot": 2,
      "type": "place_token",
      "entity": "NYC",
      "entity_type": "corporation",
      "original_id": 411
    },
    {
      "id": 263,
      "type": "pass",
      "entity": "NYC",
      "entity_type": "corporation",
      "original_id": 412
    },
    {
      "id": 264,
      "type": "run_routes",
      "entity": "NYC",
      "routes": [
        {
          "train": "5-0",
          "connections": [
            [
              "B18",
              "B16"
            ],
            [
              "B16",
              "C15"
            ],
            [
              "D6",
              "D8",
              "E9",
              "D10",
              "D12",
              "C13",
              "C15"
            ],
            [
              "C5",
              "D6"
            ]
          ]
        },
        {
          "train": "6-0",
          "connections": [
            [
              "J10",
              "I9",
              "H10",
              "H12"
            ],
            [
              "H12",
              "G13"
            ],
            [
              "G13",
              "F14",
              "F16",
              "E17"
            ],
            [
              "D20",
              "D18",
              "E17"
            ],
            [
              "D22",
              "D20"
            ]
          ]
        }
      ],
      "entity_type": "corporation",
      "original_id": 413
    },
    {
      "id": 265,
      "kind": "payout",
      "type": "dividend",
      "entity": "NYC",
      "entity_type": "corporation",
      "original_id": 414
    },
    {
      "id": 266,
      "hex": "G19",
      "tile": "14-1",
      "type": "lay_tile",
      "entity": "B&O",
      "rotation": 1,
      "entity_type": "corporation",
      "original_id": 415
    },
    {
      "id": 267,
      "hex": "G17",
      "tile": "9-4",
      "type": "lay_tile",
      "entity": "B&O",
      "rotation": 1,
      "entity_type": "corporation",
      "original_id": 416
    },
    {
      "id": 268,
      "type": "pass",
      "entity": "B&O",
      "entity_type": "corporation",
      "original_id": 417
    },
    {
      "id": 269,
      "type": "buy_train",
      "price": 900,
      "train": "6-3",
      "entity": "B&O",
      "variant": "7/8",
      "entity_type": "corporation",
      "original_id": 418
    },
    {
      "id": 270,
      "type": "pass",
      "entity": "B&O",
      "entity_type": "corporation",
      "original_id": 419
    },
    {
      "id": 271,
      "type": "sell_shares",
      "entity": "ERIE",
      "shares": [
        "ERIE_6",
        "ERIE_7",
        "ERIE_8"
      ],
      "percent": 30,
      "entity_type": "corporation",
      "share_price": 137,
      "original_id": 422
    },
    {
      "id": 272,
      "hex": "D20",
      "tile": "611-0",
      "type": "lay_tile",
      "entity": "ERIE",
      "rotation": 3,
      "entity_type": "corporation",
      "original_id": 423
    },
    {
      "id": 273,
      "city": "611-0-0",
      "slot": 1,
      "type": "place_token",
      "entity": "ERIE",
      "entity_type": "corporation",
      "original_id": 424
    },
    {
      "id": 274,
      "type": "pass",
      "entity": "ERIE",
      "entity_type": "corporation",
      "original_id": 425
    },
    {
      "id": 275,
      "type": "buy_train",
      "price": 900,
      "train": "6-4",
      "entity": "ERIE",
      "variant": "7/8",
      "entity_type": "corporation",
      "original_id": 426
    },
    {
      "id": 276,
      "type": "pass",
      "entity": "ERIE",
      "entity_type": "corporation",
      "original_id": 429
    },
    {
      "id": 277,
      "hex": "D6",
      "tile": "300-0",
      "type": "lay_tile",
      "entity": "IC",
      "rotation": 0,
      "entity_type": "corporation",
      "original_id": 430
    },
    {
      "id": 278,
      "type": "pass",
      "entity": "IC",
      "entity_type": "corporation",
      "original_id": 431
    },
    {
      "id": 279,
      "type": "run_routes",
      "entity": "IC",
      "routes": [
        {
          "train": "5-1",
          "connections": [
            [
              "B18",
              "B16"
            ],
            [
              "B16",
              "C15"
            ],
            [
              "C15",
              "C13",
              "D12",
              "D10",
              "E9",
              "E7",
              "D6"
            ],
            [
              "C5",
              "D6"
            ]
          ]
        },
        {
          "train": "6-1",
          "connections": [
            [
              "I5",
              "I3",
              "I1"
            ],
            [
              "I5",
              "I7",
              "I9",
              "H10",
              "H12"
            ],
            [
              "H12",
              "G13"
            ],
            [
              "G13",
              "F14",
              "F16",
              "E17"
            ],
            [
              "D14",
              "E15",
              "E17"
            ],
            [
              "D14",
              "C15"
            ],
            [
              "C17",
              "C15"
            ]
          ]
        }
      ],
      "entity_type": "corporation",
      "original_id": 432
    },
    {
      "id": 280,
      "kind": "payout",
      "type": "dividend",
      "entity": "IC",
      "entity_type": "corporation",
      "original_id": 447
    },
    {
      "id": 281,
      "type": "run_routes",
      "entity": "GT",
      "routes": [
        {
          "train": "5-2",
          "connections": [
            [
              "C5",
              "D6"
            ],
            [
              "C15",
              "C13",
              "D12",
              "D10",
              "E9",
              "D8",
              "D6"
            ],
            [
              "B16",
              "C15"
            ],
            [
              "B18",
              "B16"
            ]
          ]
        },
        {
          "train": "6-2",
          "connections": [
            [
              "I5",
              "I3",
              "I1"
            ],
            [
              "I5",
              "I7",
              "I9",
              "H10",
              "H12"
            ],
            [
              "H12",
              "G13"
            ],
            [
              "G13",
              "F14",
              "F16",
              "E17"
            ],
            [
              "D14",
              "E15",
              "E17"
            ],
            [
              "D14",
              "C15"
            ],
            [
              "C17",
              "C15"
            ]
          ]
        }
      ],
      "entity_type": "corporation",
      "original_id": 448
    },
    {
      "id": 282,
      "kind": "payout",
      "type": "dividend",
      "entity": "GT",
      "entity_type": "corporation",
      "original_id": 449
    },
    {
      "id": 283,
      "hex": "G13",
      "tile": "15-0",
      "type": "lay_tile",
      "entity": "NYC",
      "rotation": 0,
      "entity_type": "corporation",
      "original_id": 450
    },
    {
      "id": 284,
      "type": "pass",
      "entity": "NYC",
      "entity_type": "corporation",
      "original_id": 451
    },
    {
      "id": 285,
      "type": "run_routes",
      "entity": "NYC",
      "routes": [
        {
          "train": "5-0",
          "connections": [
            [
              "B18",
              "B16"
            ],
            [
              "B16",
              "C15"
            ],
            [
              "C15",
              "C13",
              "D12",
              "D10",
              "E9",
              "D8",
              "D6"
            ],
            [
              "C5",
              "D6"
            ]
          ]
        },
        {
          "train": "6-0",
          "connections": [
            [
              "J10",
              "I9",
              "H10",
              "H12"
            ],
            [
              "H12",
              "G13"
            ],
            [
              "E17",
              "F16",
              "F14",
              "G13"
            ],
            [
              "E17",
              "D18",
              "D20"
            ],
            [
              "D22",
              "D20"
            ]
          ]
        }
      ],
      "entity_type": "corporation",
      "original_id": 452
    },
    {
      "id": 286,
      "kind": "payout",
      "type": "dividend",
      "entity": "NYC",
      "entity_type": "corporation",
      "original_id": 453
    },
    {
      "id": 287,
      "hex": "G15",
      "tile": "57-2",
      "type": "lay_tile",
      "entity": "B&O",
      "rotation": 1,
      "entity_type": "corporation",
      "original_id": 454
    },
    {
      "id": 288,
      "hex": "G13",
      "tile": "611-1",
      "type": "lay_tile",
      "entity": "B&O",
      "rotation": 0,
      "entity_type": "corporation",
      "original_id": 455
    },
    {
      "id": 289,
      "city": "297-0-0",
      "slot": 2,
      "type": "place_token",
      "entity": "B&O",
      "entity_type": "corporation",
      "original_id": 456
    },
    {
      "id": 290,
      "type": "run_routes",
      "entity": "B&O",
      "routes": [
        {
          "train": "6-3",
          "connections": [
            [
              "I5",
              "I3",
              "I1"
            ],
            [
              "I5",
              "I7",
              "I9",
              "H10",
              "H12"
            ],
            [
              "H12",
              "G13"
            ],
            [
              "G15",
              "G13"
            ],
            [
              "G19",
              "G17",
              "G15"
            ],
            [
              "G21",
              "G19"
            ]
          ]
        }
      ],
      "entity_type": "corporation",
      "original_id": 457
    },
    {
      "id": 291,
      "kind": "payout",
      "type": "dividend",
      "entity": "B&O",
      "entity_type": "corporation",
      "original_id": 458
    },
    {
      "id": 292,
      "type": "pass",
      "entity": "B&O",
      "entity_type": "corporation",
      "original_id": 459
    },
    {
      "id": 293,
      "type": "buy_shares",
      "entity": "ERIE",
      "shares": [
        "ERIE_6",
        "ERIE_7",
        "ERIE_8"
      ],
      "entity_type": "corporation",
      "share_price": 150,
      "original_id": 460
    },
    {
      "id": 294,
      "hex": "D20",
      "tile": "51-0",
      "type": "lay_tile",
      "entity": "ERIE",
      "rotation": 3,
      "entity_type": "corporation",
      "original_id": 461
    },
    {
      "id": 295,
      "type": "pass",
      "entity": "ERIE",
      "entity_type": "corporation",
      "original_id": 462
    },
    {
      "id": 296,
      "type": "run_routes",
      "entity": "ERIE",
      "routes": [
        {
          "train": "6-4",
          "connections": [
            [
              "E17",
              "D18",
              "D20"
            ],
            [
              "E21",
              "E19",
              "D20"
            ],
            [
              "E21",
              "E23"
            ]
          ]
        }
      ],
      "entity_type": "corporation",
      "original_id": 463
    },
    {
      "id": 297,
      "kind": "payout",
      "type": "dividend",
      "entity": "ERIE",
      "entity_type": "corporation",
      "original_id": 464
    },
    {
      "id": 298,
      "type": "pass",
      "entity": "ERIE",
      "entity_type": "corporation",
      "original_id": 465
    }
  ],
  "loaded": true,
  "created_at": 1593286878,
  "updated_at": 1593367942
}